pure_di/__init__.py
pure_di/_container.py
pure_di/_factory.py
pure_di/_factory_group.py
pure_di/_inspector.py
pure_di/_provider.py
pure_di/_service_dict.py
pure_di/_types.py
pure_di/pytest.py
pure_di/utils.py
pure_di-0.0.1.dist-info/LICENSE
pure_di-0.0.1.dist-info/WHEEL
pure_di-0.0.1.dist-info/METADATA
pure_di-0.0.1.dist-info/RECORD
