Metadata-Version: 2.1
Name: pure-di
Version: 0.0.1
Summary: Simple yet powerful dependency injection framework!
Author-email: Ilya Cherezov <cherezov.ia@phystech.edu>
Requires-Python: >=3.8
Classifier: License :: OSI Approved :: MIT License
Classifier: Programming Language :: Python :: 3 :: Only
Classifier: Programming Language :: Python :: 3.8
Classifier: Programming Language :: Python :: 3.9
Classifier: Programming Language :: Python :: 3.10
Classifier: Programming Language :: Python :: 3.11
Requires-Dist: typing_extensions
Project-URL: Home, https://github.com/lionsoon/light_di
